twitter.common.threading-0.3.11-py2.7-nspkg.pth
twitter/common/threading/__init__.py
twitter/common/threading/periodic_thread.py
twitter/common/threading/stoppable_thread.py
twitter.common.threading-0.3.11.dist-info/DESCRIPTION.rst
twitter.common.threading-0.3.11.dist-info/METADATA
twitter.common.threading-0.3.11.dist-info/RECORD
twitter.common.threading-0.3.11.dist-info/WHEEL
twitter.common.threading-0.3.11.dist-info/metadata.json
twitter.common.threading-0.3.11.dist-info/namespace_packages.txt
twitter.common.threading-0.3.11.dist-info/top_level.txt
twitter.common.threading-0.3.11.dist-info/zip-safe
